mailgun_mcp/__init__.py
mailgun_mcp/__main__.py
mailgun_mcp/main.py
mailgun_mcp/utils/process_utils.py
mailgun_mcp-0.2.5.dist-info/licenses/LICENSE
mailgun_mcp-0.2.5.dist-info/METADATA
mailgun_mcp-0.2.5.dist-info/WHEEL
mailgun_mcp-0.2.5.dist-info/top_level.txt
mailgun_mcp-0.2.5.dist-info/RECORD
