Metadata-Version: 2.4
Name: mailgun-mcp
Version: 0.2.5
Summary: Unofficial MCP server for the Mailgun API
Author-email: Les Leslie <les@wedgwoodwebworks.com>
Requires-Python: >=3.13
License-File: LICENSE
Requires-Dist: fastmcp
Requires-Dist: mcp-common>=0.4.8
Requires-Dist: oneiric>=0.2.0
Dynamic: license-file
